djangocms_table/__init__.py
djangocms_table/cms_plugins.py
djangocms_table/forms.py
djangocms_table/models.py
djangocms_table/utils.py
djangocms_table/widgets.py
djangocms_table/locale/af/LC_MESSAGES/django.mo
djangocms_table/locale/af/LC_MESSAGES/django.po
djangocms_table/locale/ar/LC_MESSAGES/django.mo
djangocms_table/locale/ar/LC_MESSAGES/django.po
djangocms_table/locale/be/LC_MESSAGES/django.mo
djangocms_table/locale/be/LC_MESSAGES/django.po
djangocms_table/locale/bg/LC_MESSAGES/django.mo
djangocms_table/locale/bg/LC_MESSAGES/django.po
djangocms_table/locale/bn/LC_MESSAGES/django.mo
djangocms_table/locale/bn/LC_MESSAGES/django.po
djangocms_table/locale/ca/LC_MESSAGES/django.mo
djangocms_table/locale/ca/LC_MESSAGES/django.po
djangocms_table/locale/cmn/LC_MESSAGES/django.mo
djangocms_table/locale/cmn/LC_MESSAGES/django.po
djangocms_table/locale/cs/LC_MESSAGES/django.mo
djangocms_table/locale/cs/LC_MESSAGES/django.po
djangocms_table/locale/cy/LC_MESSAGES/django.mo
djangocms_table/locale/cy/LC_MESSAGES/django.po
djangocms_table/locale/da/LC_MESSAGES/django.mo
djangocms_table/locale/da/LC_MESSAGES/django.po
djangocms_table/locale/de/LC_MESSAGES/django.mo
djangocms_table/locale/de/LC_MESSAGES/django.po
djangocms_table/locale/el/LC_MESSAGES/django.mo
djangocms_table/locale/el/LC_MESSAGES/django.po
djangocms_table/locale/en/LC_MESSAGES/django.mo
djangocms_table/locale/en/LC_MESSAGES/django.po
djangocms_table/locale/es/LC_MESSAGES/django.mo
djangocms_table/locale/es/LC_MESSAGES/django.po
djangocms_table/locale/es_AR/LC_MESSAGES/django.mo
djangocms_table/locale/es_AR/LC_MESSAGES/django.po
djangocms_table/locale/es_BO/LC_MESSAGES/django.mo
djangocms_table/locale/es_BO/LC_MESSAGES/django.po
djangocms_table/locale/es_DO/LC_MESSAGES/django.mo
djangocms_table/locale/es_DO/LC_MESSAGES/django.po
djangocms_table/locale/et/LC_MESSAGES/django.mo
djangocms_table/locale/et/LC_MESSAGES/django.po
djangocms_table-1.2.dist-info/DESCRIPTION.rst
djangocms_table-1.2.dist-info/METADATA
djangocms_table-1.2.dist-info/metadata.json
djangocms_table-1.2.dist-info/RECORD
djangocms_table-1.2.dist-info/top_level.txt
djangocms_table-1.2.dist-info/WHEEL
